{"type":"FeatureCollection","crs":{"type":"name","properties":{"name":"EPSG:4326"}},"features":[{"type":"Feature","id":1,"geometry":{"type":"Point","coordinates":[-79.0895878955032,43.0967581049929]},"properties":{"OBJECTID":1,"supp_ID":35,"pID":139574,"Name":"Niagara Regional Police Service - 2 District","Address":"5700 VALLEY WY","Type":"NRP","SUBCAT":"Regional","URL":"http://www.nrps.com"}},{"type":"Feature","id":2,"geometry":{"type":"Point","coordinates":[-79.0861005540053,43.0974804958421]},"properties":{"OBJECTID":2,"supp_ID":36,"pID":3841,"Name":"Ontario Provincial Police - HSD-NIAGARA","Address":"5345 STANLEY AVE","Type":"OPP","SUBCAT":"Provincial","URL":"http://www.opp.ca/"}},{"type":"Feature","id":3,"geometry":{"type":"Point","coordinates":[-79.0772266015336,43.0872466389696]},"properties":{"OBJECTID":3,"supp_ID":5757,"pID":30748,"Name":"Niagara Parks Police Service Headquarters","Address":"6075 NIAGARA RIVER PY","Type":"NPP","SUBCAT":"Niagara Parks Commission","URL":"http://www.niagaraparks.com/about/niagara-parks-police.html"}}]}